<?xml version="1.0" encoding="UTF-8" ?>
<container xmlns="http://symfony.com/schema/dic/services"
           xmlns:xsi="http://www.w3.org/2001/XMLSchema-instance"
           xsi:schemaLocation="http://symfony.com/schema/dic/services http://symfony.com/schema/dic/services/services-1.0.xsd">

    <parameters>
        <parameter key="rz.category_page.page.service.category.class">Rz\CategoryPageBundle\Page\Service\CategoryPageService</parameter>
        <parameter key="rz.category_page.page.service.category.name">Category</parameter>
        <parameter key="rz.category_page.page.service.category_canonical.class">Rz\CategoryPageBundle\Page\Service\CategoryCanonicalPageService</parameter>
        <parameter key="rz.category_page.page.service.category_canonical.name">Category Canonical</parameter>
    </parameters>

    <services>
        <service id="rz.category_page.page.service.category" class="%rz.category_page.page.service.category.class%">
            <tag name="sonata.page"/>
            <argument>%rz.category_page.page.service.category.name%</argument>
            <argument type="service" id="sonata.page.template_manager" />
            <argument type="service" id="sonata.seo.page" />
            <argument type="service" id="sonata.page.router" />
        </service>
        <service id="rz.category_page.page.service.category_canonical" class="%rz.category_page.page.service.category_canonical.class%">
            <tag name="sonata.page"/>
            <argument>%rz.category_page.page.service.category_canonical.name%</argument>
            <argument type="service" id="sonata.page.template_manager" />
            <argument type="service" id="sonata.seo.page" />
        </service>
    </services>
</container>
